LICENSE
README.md
setup.py
GCRCatalogs/SCHEMA.md
GCRCatalogs/__init__.py
GCRCatalogs/agn.py
GCRCatalogs/agncombined.py
GCRCatalogs/alphaq.py
GCRCatalogs/alphaq_addon.py
GCRCatalogs/base_config.py
GCRCatalogs/butler_interface.py
GCRCatalogs/buzzard.py
GCRCatalogs/catalog_helpers.py
GCRCatalogs/composite.py
GCRCatalogs/cosmodc2.py
GCRCatalogs/cosmodc2_parquet.py
GCRCatalogs/cosmology.py
GCRCatalogs/dc2_dia_object.py
GCRCatalogs/dc2_dia_source.py
GCRCatalogs/dc2_dm_catalog.py
GCRCatalogs/dc2_forced_source.py
GCRCatalogs/dc2_matched_table.py
GCRCatalogs/dc2_metacal.py
GCRCatalogs/dc2_object.py
GCRCatalogs/dc2_photoz_parquet.py
GCRCatalogs/dc2_source.py
GCRCatalogs/dc2_truth.py
GCRCatalogs/dc2_truth_match.py
GCRCatalogs/dc2_truth_parquet.py
GCRCatalogs/dr_register.py
GCRCatalogs/eimage.py
GCRCatalogs/instance_catalog.py
GCRCatalogs/parquet.py
GCRCatalogs/parse_utils.py
GCRCatalogs/photoz.py
GCRCatalogs/photoz_calibrate.py
GCRCatalogs/photoz_magerr.py
GCRCatalogs/redmagic.py
GCRCatalogs/redmapper.py
GCRCatalogs/reference_catalog.py
GCRCatalogs/register.py
GCRCatalogs/root_dir_manager.py
GCRCatalogs/user_config.py
GCRCatalogs/user_config_mgr.py
GCRCatalogs/utils.py
GCRCatalogs/version.py
GCRCatalogs/wazp.py
GCRCatalogs/catalog_configs/AGN_mean_mags_v1.1.4.yaml
GCRCatalogs/catalog_configs/_cosmoDC2_check.yaml
GCRCatalogs/catalog_configs/_dc2_dia_object_meta.yaml
GCRCatalogs/catalog_configs/_dc2_dia_source_meta.yaml
GCRCatalogs/catalog_configs/_dc2_forced_source_meta.yaml
GCRCatalogs/catalog_configs/_dc2_object_meta.yaml
GCRCatalogs/catalog_configs/_dc2_photoz_parquet.yaml
GCRCatalogs/catalog_configs/_dc2_source_meta.yaml
GCRCatalogs/catalog_configs/_dc2_truth_match_meta.yaml
GCRCatalogs/catalog_configs/_wazp_v1.0_meta.yaml
GCRCatalogs/catalog_configs/base5000_v1.1.1.yaml
GCRCatalogs/catalog_configs/base5000_v1.1.1_9431_9812.yaml
GCRCatalogs/catalog_configs/base5000_v1.1.1_9556.yaml
GCRCatalogs/catalog_configs/base5000_v1.1.1_image.yaml
lsstdesc_gcr_catalogs.egg-info/PKG-INFO
lsstdesc_gcr_catalogs.egg-info/SOURCES.txt
lsstdesc_gcr_catalogs.egg-info/dependency_links.txt
lsstdesc_gcr_catalogs.egg-info/requires.txt
lsstdesc_gcr_catalogs.egg-info/top_level.txt
