Metadata-Version: 2.4
Name: lsstdesc-gcr-catalogs
Version: 1.10.1
Summary: Catalog repo for LSST DESC
Home-page: https://github.com/LSSTDESC/gcr-catalogs
Author: Yao-Yuan Mao
Author-email: yymao.astro@gmail.com
Maintainer: Yao-Yuan Mao
Maintainer-email: yymao.astro@gmail.com
License: MIT
Keywords: GCR
Classifier: Intended Audience :: Developers
Classifier: Intended Audience :: Science/Research
Classifier: License :: OSI Approved :: MIT License
Classifier: Programming Language :: Python :: 3.6
License-File: LICENSE
Requires-Dist: requests
Requires-Dist: pyyaml
Requires-Dist: numpy
Requires-Dist: astropy
Requires-Dist: GCR>=0.9.2
Provides-Extra: full
Requires-Dist: h5py; extra == "full"
Requires-Dist: healpy; extra == "full"
Requires-Dist: pandas; extra == "full"
Requires-Dist: pyarrow; extra == "full"
Requires-Dist: tables; extra == "full"
Dynamic: author
Dynamic: author-email
Dynamic: classifier
Dynamic: home-page
Dynamic: keywords
Dynamic: license
Dynamic: license-file
Dynamic: maintainer
Dynamic: maintainer-email
Dynamic: provides-extra
Dynamic: requires-dist
Dynamic: summary
